picklepie/__init__.py
picklepie/__eval/__init__.py
picklepie/ai/__init__.py
picklepie/ai/cb/__init__.py
picklepie/ai/cv/__init__.py
picklepie/ai/cv/__haarcascade/__init__.py
picklepie/ai/cv/__haarcascade/haarcascade_car.xml
picklepie/ai/cv/__haarcascade/haarcascade_eye.xml
picklepie/ai/cv/__haarcascade/haarcascade_eye_tree_eyeglasses.xml
picklepie/ai/cv/__haarcascade/haarcascade_frontalcatface.xml
picklepie/ai/cv/__haarcascade/haarcascade_frontalcatface_extended.xml
picklepie/ai/cv/__haarcascade/haarcascade_frontalface_alt.xml
picklepie/ai/cv/__haarcascade/haarcascade_frontalface_alt2.xml
picklepie/ai/cv/__haarcascade/haarcascade_frontalface_alt_tree.xml
picklepie/ai/cv/__haarcascade/haarcascade_frontalface_default.xml
picklepie/ai/cv/__haarcascade/haarcascade_fullbody.xml
picklepie/ai/cv/__haarcascade/haarcascade_lefteye_2splits.xml
picklepie/ai/cv/__haarcascade/haarcascade_licence_plate_rus_16stages.xml
picklepie/ai/cv/__haarcascade/haarcascade_lowerbody.xml
picklepie/ai/cv/__haarcascade/haarcascade_profileface.xml
picklepie/ai/cv/__haarcascade/haarcascade_righteye_2splits.xml
picklepie/ai/cv/__haarcascade/haarcascade_russian_plate_number.xml
picklepie/ai/cv/__haarcascade/haarcascade_smile.xml
picklepie/ai/cv/__haarcascade/haarcascade_upperbody.xml
picklepie/ai/nlp/__init__.py
picklepie/ai/nlp/lang/__init__.py
picklepie/ai/ocr/__init__.py
picklepie/ai/ocr/pdf/__init__.py
picklepie/ai/sr/__init__.py
picklepie/base/__init__.py
picklepie/base/file/__init__.py
picklepie/chart/__init__.py
picklepie/chart/boxplot/__init__.py
picklepie/chart/boxplot/outlier.py
picklepie/chart/correlation/__init__.py
picklepie/chart/cumulative_gain/__init__.py
picklepie/chart/density/__init__.py
picklepie/chart/histogram/__init__.py
picklepie/chart/lift/__init__.py
picklepie/chart/pairplot/__init__.py
picklepie/chart/precision_recall/__init__.py
picklepie/chart/roc/__init__.py
picklepie/chart/scatterplot/__init__.py
picklepie/data/__init__.py
picklepie/data/column/__init__.py
picklepie-0.0.2.dist-info/LICENSE.txt
picklepie-0.0.2.dist-info/METADATA
picklepie-0.0.2.dist-info/WHEEL
picklepie-0.0.2.dist-info/top_level.txt
picklepie-0.0.2.dist-info/RECORD
