Metadata-Version: 2.1
Name: picklepie
Version: 0.0.2
Summary: a Python Package
Home-page: https://github.com/ah4d1/picklepie
Author: Ahadi Aprianto
Author-email: support@pickle.id
Project-URL: Bug Tracker, https://github.com/ah4d1/picklepie
Classifier: Programming Language :: Python :: 3
Classifier: License :: OSI Approved :: BSD License
Classifier: Operating System :: OS Independent
Requires-Python: >=3.6
License-File: LICENSE.txt
Requires-Dist: ChatterBot (==1.0.4)
Requires-Dist: findspark (>=1.4.2)
Requires-Dist: googletrans (==3.1.0a0)
Requires-Dist: gTTS (>=2.2.3)
Requires-Dist: imblearn (>=0.0)
Requires-Dist: imbalanced-learn (>=0.8.0)
Requires-Dist: keras (>=2.4.3)
Requires-Dist: kneed (>=0.7.0)
Requires-Dist: langdetect (>=1.0.9)
Requires-Dist: matplotlib (>=3.3.1)
Requires-Dist: mlxtend (>=0.18.0)
Requires-Dist: multipledispatch (>=0.6.0)
Requires-Dist: nltk (>=3.5)
Requires-Dist: numpy (>=1.19.1)
Requires-Dist: opencv-python (>=4.5.3)
Requires-Dist: openpyxl (>=3.0.7)
Requires-Dist: playsound (>=1.2.2)
Requires-Dist: pydub (>=0.25.1)
Requires-Dist: pyodbc (>=4.0.30)
Requires-Dist: PyPDF2 (>=1.26.0)
Requires-Dist: pytesseract (>=0.3.8)
Requires-Dist: Sastrawi (>=1.0.1)
Requires-Dist: seaborn (>=0.11.1)
Requires-Dist: sklearn (>=0.0)
Requires-Dist: scikit-learn (>=0.24.2)
Requires-Dist: scikit-plot (>=0.3.7)
Requires-Dist: sounddevice (>=0.4.1)
Requires-Dist: SoundFile (>=0.10.2)
Requires-Dist: SpeechRecognition (>=3.8.1)
Requires-Dist: statsmodels (>=0.12.2)
Requires-Dist: tensorflow (>=2.5.0)
